{
  "id": "dungeontrain:animals",
  "entries": [
    {
      "text": "Puppies"
    },
    {
      "text": "Bats"
    },
    {
      "text": "Small Chickens"
    },
    {
      "text": "Chicks"
    },
    {
      "text": "Unicorns"
    },
    {
      "text": "Great White"
    },
    {
      "text": "Mares"
    },
    {
      "text": "Lions"
    },
    {
      "text": "Cows"
    },
    {
      "text": "Rats"
    },
    {
      "text": "Mice"
    },
    {
      "text": "Hippos"
    },
    {
      "text": "Kittens"
    },
    {
      "text": "Dogs"
    },
    {
      "text": "Hamsters"
    },
    {
      "text": "Dragons"
    },
    {
      "text": "Earth Worms"
    },
    {
      "text": "Ants"
    },
    {
      "text": "Spiders"
    },
    {
      "text": "Snakes"
    },
    {
      "text": "The Fae"
    },
    {
      "text": "Monkies"
    },
    {
      "text": "Octopuses"
    }
  ]
}
