{
  "id": "adventureitemnames:math",
  "entries": [
    {
      "text": "무한"
    },
    {
      "text": "합리성"
    },
    {
      "text": "수학적 확실성"
    },
    {
      "text": "기하학"
    },
    {
      "text": "삼각법"
    },
    {
      "text": "과학"
    },
    {
      "text": "비합리성"
    },
    {
      "text": "파이"
    },
    {
      "text": "무리수"
    },
    {
      "text": "분수"
    },
    {
      "text": "숫자"
    },
    {
      "text": "제곱근"
    },
    {
      "text": "마이너스 일"
    },
    {
      "text": "영"
    },
    {
      "text": "백만"
    },
    {
      "text": "백"
    },
    {
      "text": "다섯"
    },
    {
      "text": "칠 점 이"
    },
    {
      "text": "수학"
    },
    {
      "text": "정수"
    },
    {
      "text": "함수"
    },
    {
      "text": "알고리즘"
    },
    {
      "text": "알고리즘의 희열"
    }
  ]
}
