{
  "schemaVersion": 8,
  "mirror": { "x": true, "y": true, "z": true, "v": true },
  "variants": {
    "3,0,2": { "lockId": 1, "states": [{"state": "minecraft:oak_planks", "weight": 5}, "minecraft:stripped_oak_wood[axis=y]", "minecraft:oak_wood[axis=y]"] },
    "2,0,2": { "lockId": 1, "states": [{"state": "minecraft:oak_planks", "weight": 5}, "minecraft:stripped_oak_wood[axis=y]", "minecraft:oak_wood[axis=y]"] },
    "4,0,2": { "lockId": 1, "states": [{"state": "minecraft:oak_planks", "weight": 5}, "minecraft:stripped_oak_wood[axis=y]", "minecraft:oak_wood[axis=y]"] },
    "1,0,2": { "lockId": 1, "states": [{"state": "minecraft:oak_planks", "weight": 5}, "minecraft:stripped_oak_wood[axis=y]", "minecraft:oak_wood[axis=y]"] },
    "5,0,2": { "lockId": 1, "states": [{"state": "minecraft:oak_planks", "weight": 5}, "minecraft:stripped_oak_wood[axis=y]", "minecraft:oak_wood[axis=y]"] },
    "6,0,2": { "lockId": 2, "states": [{"state": "minecraft:oak_planks", "weight": 5}, "minecraft:stripped_oak_wood[axis=y]"] },
    "0,0,2": { "lockId": 2, "states": [{"state": "minecraft:oak_planks", "weight": 5}, "minecraft:stripped_oak_wood[axis=y]"] },
    "6,0,3": { "lockId": 2, "states": [{"state": "minecraft:oak_planks", "weight": 5}, "minecraft:stripped_oak_wood[axis=y]"] },
    "6,0,1": { "lockId": 2, "states": [{"state": "minecraft:oak_planks", "weight": 5}, "minecraft:stripped_oak_wood[axis=y]"] },
    "0,0,3": { "lockId": 2, "states": [{"state": "minecraft:oak_planks", "weight": 5}, "minecraft:stripped_oak_wood[axis=y]"] },
    "0,0,1": { "lockId": 2, "states": [{"state": "minecraft:oak_planks", "weight": 5}, "minecraft:stripped_oak_wood[axis=y]"] },
    "6,0,4": { "lockId": 2, "states": [{"state": "minecraft:oak_planks", "weight": 5}, "minecraft:stripped_oak_wood[axis=y]"] },
    "6,0,0": { "lockId": 2, "states": [{"state": "minecraft:oak_planks", "weight": 5}, "minecraft:stripped_oak_wood[axis=y]"] },
    "0,0,4": { "lockId": 2, "states": [{"state": "minecraft:oak_planks", "weight": 5}, "minecraft:stripped_oak_wood[axis=y]"] },
    "0,0,0": { "lockId": 2, "states": [{"state": "minecraft:oak_planks", "weight": 5}, "minecraft:stripped_oak_wood[axis=y]"] },
    "5,0,4": { "lockId": 2, "states": [{"state": "minecraft:oak_planks", "weight": 5}, "minecraft:stripped_oak_wood[axis=y]"] },
    "5,0,0": { "lockId": 2, "states": [{"state": "minecraft:oak_planks", "weight": 5}, "minecraft:stripped_oak_wood[axis=y]"] },
    "1,0,4": { "lockId": 2, "states": [{"state": "minecraft:oak_planks", "weight": 5}, "minecraft:stripped_oak_wood[axis=y]"] },
    "1,0,0": { "lockId": 2, "states": [{"state": "minecraft:oak_planks", "weight": 5}, "minecraft:stripped_oak_wood[axis=y]"] },
    "4,0,4": { "lockId": 2, "states": [{"state": "minecraft:oak_planks", "weight": 5}, "minecraft:stripped_oak_wood[axis=y]"] },
    "4,0,0": { "lockId": 2, "states": [{"state": "minecraft:oak_planks", "weight": 5}, "minecraft:stripped_oak_wood[axis=y]"] },
    "2,0,4": { "lockId": 2, "states": [{"state": "minecraft:oak_planks", "weight": 5}, "minecraft:stripped_oak_wood[axis=y]"] },
    "2,0,0": { "lockId": 2, "states": [{"state": "minecraft:oak_planks", "weight": 5}, "minecraft:stripped_oak_wood[axis=y]"] },
    "3,0,4": { "lockId": 2, "states": [{"state": "minecraft:oak_planks", "weight": 5}, "minecraft:stripped_oak_wood[axis=y]"] },
    "3,0,0": { "lockId": 2, "states": [{"state": "minecraft:oak_planks", "weight": 5}, "minecraft:stripped_oak_wood[axis=y]"] },
    "5,0,1": { "lockId": 3, "states": [{"state": "minecraft:oak_planks", "weight": 10}, "minecraft:stripped_oak_wood[axis=y]"] },
    "5,0,3": { "lockId": 3, "states": [{"state": "minecraft:oak_planks", "weight": 10}, "minecraft:stripped_oak_wood[axis=y]"] },
    "1,0,1": { "lockId": 3, "states": [{"state": "minecraft:oak_planks", "weight": 10}, "minecraft:stripped_oak_wood[axis=y]"] },
    "1,0,3": { "lockId": 3, "states": [{"state": "minecraft:oak_planks", "weight": 10}, "minecraft:stripped_oak_wood[axis=y]"] },
    "4,0,1": { "lockId": 3, "states": [{"state": "minecraft:oak_planks", "weight": 10}, "minecraft:stripped_oak_wood[axis=y]"] },
    "4,0,3": { "lockId": 3, "states": [{"state": "minecraft:oak_planks", "weight": 10}, "minecraft:stripped_oak_wood[axis=y]"] },
    "2,0,1": { "lockId": 3, "states": [{"state": "minecraft:oak_planks", "weight": 10}, "minecraft:stripped_oak_wood[axis=y]"] },
    "2,0,3": { "lockId": 3, "states": [{"state": "minecraft:oak_planks", "weight": 10}, "minecraft:stripped_oak_wood[axis=y]"] },
    "3,0,1": { "lockId": 3, "states": [{"state": "minecraft:oak_planks", "weight": 10}, "minecraft:stripped_oak_wood[axis=y]"] },
    "3,0,3": { "lockId": 3, "states": [{"state": "minecraft:oak_planks", "weight": 10}, "minecraft:stripped_oak_wood[axis=y]"] }
  }
}
