{
  "copper": {
    "name": "copper",
    "minLevel": 36,
    "maxLevel": 50,
    "phases": [
      "OVERWORLD",
      "VOID",
      "END",
      "UPSIDE_DOWN"
    ]
  },
  "deepdark": {
    "name": "deepdark",
    "minLevel": 87,
    "maxLevel": 120,
    "phases": [
      "OVERWORLD",
      "VOID",
      "END",
      "UPSIDE_DOWN"
    ]
  },
  "desert": {
    "name": "desert",
    "minLevel": 11,
    "maxLevel": 35,
    "phases": [
      "OVERWORLD",
      "VOID",
      "END",
      "UPSIDE_DOWN"
    ]
  },
  "mud": {
    "name": "mud",
    "minLevel": 121,
    "maxLevel": 130,
    "phases": [
      "OVERWORLD",
      "VOID",
      "END",
      "UPSIDE_DOWN"
    ]
  },
  "nether": {
    "name": "nether",
    "phases": [
      "NETHER",
      "END"
    ]
  },
  "obsidian": {
    "name": "obsidian",
    "minLevel": 71,
    "maxLevel": 86,
    "phases": [
      "OVERWORLD",
      "VOID",
      "END",
      "UPSIDE_DOWN"
    ]
  },
  "quartz": {
    "name": "quartz",
    "minLevel": 51,
    "maxLevel": 70,
    "phases": [
      "OVERWORLD",
      "VOID",
      "END",
      "UPSIDE_DOWN"
    ]
  },
  "stone": {
    "name": "stone",
    "maxLevel": 10,
    "phases": [
      "OVERWORLD",
      "VOID",
      "END",
      "UPSIDE_DOWN"
    ]
  },
  "wood_oak": {
    "name": "wood_oak",
    "minLevel": 131,
    "maxLevel": 200,
    "phases": [
      "OVERWORLD",
      "VOID",
      "END",
      "UPSIDE_DOWN"
    ]
  }
}