{
  "id": "adventureitemnames:it_has_a",
  "entries": [
    {
      "text": "basag"
    },
    {
      "text": "matalas"
    },
    {
      "text": "banayad"
    },
    {
      "text": "madilim"
    },
    {
      "text": "magaan"
    },
    {
      "text": "maliwanag"
    },
    {
      "text": "pangit"
    },
    {
      "text": "maganda"
    },
    {
      "text": "kaakit-akit"
    },
    {
      "text": "nakakatakot"
    },
    {
      "text": "kilala"
    },
    {
      "text": "karapat-dapat"
    },
    {
      "text": "kahiya-hiya"
    },
    {
      "text": "nakakikilabot"
    },
    {
      "text": "nakasisindak"
    },
    {
      "text": "maalinsangan"
    },
    {
      "text": "parang dumi"
    },
    {
      "text": "maka-diyos"
    },
    {
      "text": "maka-ina"
    },
    {
      "text": "maka-ama"
    },
    {
      "text": "malalim"
    },
    {
      "text": "mababaw"
    },
    {
      "text": "prangka"
    },
    {
      "text": "mataba"
    },
    {
      "text": "umuuga"
    },
    {
      "text": "masuwerte"
    },
    {
      "text": "kakaibang tangkad"
    },
    {
      "text": "kakaibang kahel"
    },
    {
      "text": "malaki"
    },
    {
      "text": "maliit"
    },
    {
      "text": "hindi pantay"
    },
    {
      "text": "maganda"
    },
    {
      "text": "kaaya-aya"
    },
    {
      "text": "nakakadiri"
    },
    {
      "text": "kadire-dire"
    },
    {
      "text": "multuhin"
    }
  ]
}
