{
  "id": "adventureitemnames:title_post_prefix",
  "entries": [
    {
      "text": "Segala Perkara"
    },
    {
      "text": "Yang Dibuang"
    },
    {
      "text": "Manusia"
    },
    {
      "text": "Wabak"
    },
    {
      "text": "Semua"
    },
    {
      "text": "Segala Perkara"
    },
    {
      "text": "Penguasa"
    },
    {
      "text": "Raja"
    },
    {
      "text": "Bilah"
    },
    {
      "text": "Yang Terlucut"
    },
    {
      "text": "Zaman Akhir"
    },
    {
      "text": "Corona."
    },
    {
      "text": "Kekayaan"
    },
    {
      "text": "Lendir"
    },
    {
      "text": "Kemasyhuran"
    },
    {
      "text": "Jari"
    },
    {
      "text": "Perkara Luar Biasa"
    },
    {
      "text": "Kereta Api"
    },
    {
      "text": "Alex"
    },
    {
      "text": "Ketakterbatasan"
    },
    {
      "text": "Keluasan"
    },
    {
      "text": "Sebelah Kasut Kecil"
    },
    {
      "text": "Pemikiran Rasional"
    },
    {
      "text": "Kekakuan"
    },
    {
      "text": "Mitologi"
    },
    {
      "text": "Zaman"
    },
    {
      "text": "Impian"
    },
    {
      "text": "Mimpi Ngeri"
    },
    {
      "text": "Seni"
    },
    {
      "text": "Keagungan"
    },
    {
      "text": "Kebulatan"
    },
    {
      "text": "Penerbangan"
    },
    {
      "text": "Bulu"
    },
    {
      "text": "Toponimi"
    }
  ]
}
