{
  "id": "adventureitemnames:colors",
  "entries": [
    {
      "text": "赤红"
    },
    {
      "text": "橙黄"
    },
    {
      "text": "金黄"
    },
    {
      "text": "翠绿"
    },
    {
      "text": "湛蓝"
    },
    {
      "text": "青蓝"
    },
    {
      "text": "紫罗兰"
    },
    {
      "text": "苍白"
    },
    {
      "text": "漆黑"
    },
    {
      "text": "棕褐"
    },
    {
      "text": "品红"
    },
    {
      "text": "浅褐"
    },
    {
      "text": "橄榄"
    },
    {
      "text": "暗红"
    },
    {
      "text": "海军蓝"
    },
    {
      "text": "海蓝"
    },
    {
      "text": "绿松石"
    },
    {
      "text": "银白"
    },
    {
      "text": "酸橙绿"
    },
    {
      "text": "蓝绿"
    },
    {
      "text": "靛蓝"
    },
    {
      "text": "紫晶"
    },
    {
      "text": "粉红"
    },
    {
      "text": "灰色"
    },
    {
      "text": "灰白"
    },
    {
      "text": "深蓝"
    },
    {
      "text": "嫩粉"
    }
  ]
}
